Exploity/__init__.py
Exploity-0.0.dist-info/METADATA
Exploity-0.0.dist-info/WHEEL
Exploity-0.0.dist-info/top_level.txt
Exploity-0.0.dist-info/RECORD
