Metadata-Version: 2.1
Name: Exploity
Version: 0.0
Summary: Exploit development framework
Home-page: UNKNOWN
Author: Awais khan
Author-email: UNKNOWN
License: UNKNOWN
Platform: UNKNOWN
